rpy_symmetry/__init__.py
rpy_symmetry/rpy_symmetry.py
rpy_symmetry-0.3.0.dist-info/METADATA
rpy_symmetry-0.3.0.dist-info/WHEEL
rpy_symmetry-0.3.0.dist-info/top_level.txt
rpy_symmetry-0.3.0.dist-info/RECORD
