Metadata-Version: 2.4
Name: rpy_symmetry
Version: 0.3.0
Summary: Light weight bridge from `R` to `python` of the [`symmetry` R-module](https://cran.r-project.org/web/packages/symmetry).
Author: Joran R. Angevaare
Maintainer: Joran R. Angevaare
License: MIT
Project-URL: homepage, https://github.com/JoranAngevaare/rpy_symmetry
Project-URL: documentation, https://github.com/JoranAngevaare/rpy_symmetry/blob/master/examples/Example.ipynb
Project-URL: repository, https://github.com/JoranAngevaare/rpy_symmetry
Classifier: Intended Audience :: Science/Research
Classifier: Development Status :: 5 - Production/Stable
Classifier: Natural Language :: English
Classifier: Programming Language :: Python :: 3.8
Classifier: Programming Language :: Python :: 3.9
Classifier: Programming Language :: Python :: 3.10
Classifier: Programming Language :: Python :: 3.11
Classifier: Intended Audience :: Science/Research
Classifier: Programming Language :: Python :: Implementation :: CPython
Requires-Python: >=3.8
Requires-Dist: numpy
Requires-Dist: rpy2
Provides-Extra: test
Requires-Dist: coverage; extra == "test"
Requires-Dist: coveralls; extra == "test"
Requires-Dist: ipython; extra == "test"
Requires-Dist: matplotlib; extra == "test"
Requires-Dist: nbmake; extra == "test"
Requires-Dist: pytest; extra == "test"
Requires-Dist: tqdm; extra == "test"
